cfdmod/__init__.py
cfdmod/logger.py
cfdmod/utils.py
cfdmod/analysis/__init__.py
cfdmod/analysis/inflow/__init__.py
cfdmod/analysis/inflow/functions.py
cfdmod/analysis/inflow/profile.py
cfdmod/api/__init__.py
cfdmod/api/configs/hashable.py
cfdmod/api/geometry/STL.py
cfdmod/api/geometry/region_meshing.py
cfdmod/api/geometry/transformation_config.py
cfdmod/api/vtk/probe_vtm.py
cfdmod/api/vtk/write_vtk.py
cfdmod/use_cases/__init__.py
cfdmod/use_cases/altimetry/__init__.py
cfdmod/use_cases/altimetry/__main__.py
cfdmod/use_cases/altimetry/figure.py
cfdmod/use_cases/altimetry/main.py
cfdmod/use_cases/altimetry/plots.py
cfdmod/use_cases/altimetry/probe.py
cfdmod/use_cases/altimetry/section.py
cfdmod/use_cases/altimetry/shed.py
cfdmod/use_cases/altimetry/vertices.py
cfdmod/use_cases/loft/__init__.py
cfdmod/use_cases/loft/__main__.py
cfdmod/use_cases/loft/functions.py
cfdmod/use_cases/loft/main.py
cfdmod/use_cases/loft/parameters.py
cfdmod/use_cases/pressure/__init__.py
cfdmod/use_cases/pressure/__main__.py
cfdmod/use_cases/pressure/base_config.py
cfdmod/use_cases/pressure/chunking.py
cfdmod/use_cases/pressure/cp_config.py
cfdmod/use_cases/pressure/cp_data.py
cfdmod/use_cases/pressure/extreme_values.py
cfdmod/use_cases/pressure/geometry.py
cfdmod/use_cases/pressure/main.py
cfdmod/use_cases/pressure/output.py
cfdmod/use_cases/pressure/path_manager.py
cfdmod/use_cases/pressure/statistics.py
cfdmod/use_cases/pressure/force/Cf_config.py
cfdmod/use_cases/pressure/force/Cf_data.py
cfdmod/use_cases/pressure/force/Cf_geom.py
cfdmod/use_cases/pressure/force/__init__.py
cfdmod/use_cases/pressure/force/__main__.py
cfdmod/use_cases/pressure/force/main.py
cfdmod/use_cases/pressure/moment/Cm_config.py
cfdmod/use_cases/pressure/moment/Cm_data.py
cfdmod/use_cases/pressure/moment/Cm_geom.py
cfdmod/use_cases/pressure/moment/__init__.py
cfdmod/use_cases/pressure/moment/__main__.py
cfdmod/use_cases/pressure/moment/main.py
cfdmod/use_cases/pressure/shape/Ce_config.py
aerosim_cfdmod-1.1.4.dist-info/METADATA
aerosim_cfdmod-1.1.4.dist-info/WHEEL
aerosim_cfdmod-1.1.4.dist-info/licenses/LICENSE
aerosim_cfdmod-1.1.4.dist-info/RECORD
