Metadata-Version: 2.4
Name: aerosim-cfdmod
Version: 1.1.4
Summary: Tools for analysis of CFD cases
Project-URL: Homepage, https://github.com/AeroSim-CFD/cfdmod
Project-URL: Repository, https://github.com/AeroSim-CFD/cfdmod
Author-email: Waine Oliveira Jr <waine@aerosim.io>, Pablo Penas <pablo@aerosim.io>
License-Expression: Apache-2.0
License-File: LICENSE
Requires-Python: ~=3.10
Requires-Dist: colorama<0.5,>=0.4.6
Requires-Dist: matplotlib<4,>=3.7.3
Requires-Dist: numpy<3,>=1.24
Requires-Dist: pandas<3,>=2.1.0
Requires-Dist: pyarrow<20,>=19.0.0
Requires-Dist: pydantic<3,>=2.3
Requires-Dist: ruamel-yaml<0.19,>=0.18.5
Requires-Dist: scipy<2,>=1.11.2
Requires-Dist: tables<4,>=3.9.1
Provides-Extra: docs
Requires-Dist: myst-parser<5,>=4.0; extra == 'docs'
Requires-Dist: nbsphinx<0.10,>=0.9.3; extra == 'docs'
Requires-Dist: sphinx-autobuild>=2021.3.14; extra == 'docs'
Requires-Dist: sphinx-book-theme<2,>=1.0.1; extra == 'docs'
Requires-Dist: sphinxcontrib-bibtex<3,>=2.6.1; extra == 'docs'
Provides-Extra: geometry
Requires-Dist: pymeshlab<2024,>=2023; extra == 'geometry'
Requires-Dist: trimesh<5,>=4.0; extra == 'geometry'
Provides-Extra: lnas
Requires-Dist: aerosim-lnas<0.7,>=0.6.0; extra == 'lnas'
Provides-Extra: notebook
Requires-Dist: ipykernel<7,>=6.25.2; extra == 'notebook'
Requires-Dist: ipython<9,>=8.15.0; extra == 'notebook'
Requires-Dist: jupyter<2,>=1.0.0; extra == 'notebook'
Provides-Extra: vtk
Requires-Dist: pyvista<0.45,>=0.44; extra == 'vtk'
Requires-Dist: vtk<10,>=9.2.6; extra == 'vtk'
